freq_mob/__init__.py
freq_mob/freq_mob.py
freq_mob-0.11.dist-info/LICENSE.txt
freq_mob-0.11.dist-info/METADATA
freq_mob-0.11.dist-info/WHEEL
freq_mob-0.11.dist-info/top_level.txt
freq_mob-0.11.dist-info/RECORD
