Metadata-Version: 2.1
Name: freq-mob
Version: 0.11
Summary: Monotonic Optimal Binning for Frequency Models
Home-page: https://github.com/statcompute/freq_mob
Author: WenSui Liu
Author-email: liuwensui@gmail.com
Classifier: Programming Language :: Python :: 3
Classifier: License :: OSI Approved :: MIT License
Classifier: Operating System :: OS Independent
License-File: LICENSE.txt
Requires-Dist: numpy
Requires-Dist: scipy
Requires-Dist: sklearn
Requires-Dist: lightgbm
Requires-Dist: tabulate
